myorm/__init__.py
myorm/dbobject.py
myorm/exceptions.py
myorm/fields.py
myorm/managers.py
myorm/migrations.py
myorm/queryset.py
myorm/tests.py
myorm/adaptors/__init__.py
myorm/adaptors/db2.py
myorm/adaptors/mysql.py
myorm/adaptors/oracle.py
myorm/adaptors/sqlite.py
myorm-0.5.1.dist-info/METADATA
myorm-0.5.1.dist-info/WHEEL
myorm-0.5.1.dist-info/top_level.txt
myorm-0.5.1.dist-info/RECORD
