Metadata-Version: 2.1
Name: myorm
Version: 0.5.1
Summary: Provides a simple ORM for MySQL, PostgreSQL and SQLite.
Home-page: UNKNOWN
Author: Christian Kokoska
Author-email: christian@eternalconcert.de
License: GPLv3
Platform: UNKNOWN
